cursorcult/__init__.py
cursorcult/ccverify.py
cursorcult/cli.py
cursorcult/constants.py
cursorcult/core.py
cursorcult-0.14.13.dist-info/licenses/LICENSE
cursorcult-0.14.13.dist-info/METADATA
cursorcult-0.14.13.dist-info/WHEEL
cursorcult-0.14.13.dist-info/entry_points.txt
cursorcult-0.14.13.dist-info/top_level.txt
cursorcult-0.14.13.dist-info/RECORD
