Metadata-Version: 2.4
Name: cursorcult
Version: 0.14.13
Summary: CLI to list and link CursorCult rules.
Author: Will Wieselquist
License: Unlicense
Project-URL: Homepage, https://github.com/CursorCult/_CursorCult.git
Project-URL: Repository, https://github.com/CursorCult/_CursorCult.git
Project-URL: Issues, https://github.com/CursorCult/_CursorCult.git
Keywords: cursor,rules,cursorcult
Classifier: License :: Public Domain
Classifier: Programming Language :: Python :: 3
Classifier: Environment :: Console
Classifier: Topic :: Software Development
Requires-Python: >=3.9
License-File: LICENSE
Requires-Dist: lizard>=1.17.10
Requires-Dist: tree_sitter<0.22,>=0.21.3
Requires-Dist: tree-sitter-languages>=1.10.2
Dynamic: license-file
